caniuseonlywheels/__init__.py
caniuseonlywheels/__main__.py
caniuseonlywheels/command.py
caniuseonlywheels/dependencies.py
caniuseonlywheels/distlib/__init__.py
caniuseonlywheels/distlib/_backport/__init__.py
caniuseonlywheels/distlib/_backport/misc.py
caniuseonlywheels/distlib/_backport/shutil.py
caniuseonlywheels/distlib/_backport/sysconfig.cfg
caniuseonlywheels/distlib/_backport/sysconfig.py
caniuseonlywheels/distlib/_backport/tarfile.py
caniuseonlywheels/distlib/compat.py
caniuseonlywheels/distlib/database.py
caniuseonlywheels/distlib/index.py
caniuseonlywheels/distlib/locators.py
caniuseonlywheels/distlib/manifest.py
caniuseonlywheels/distlib/markers.py
caniuseonlywheels/distlib/metadata.py
caniuseonlywheels/distlib/resources.py
caniuseonlywheels/distlib/scripts.py
caniuseonlywheels/distlib/t32.exe
caniuseonlywheels/distlib/t64-arm.exe
caniuseonlywheels/distlib/t64.exe
caniuseonlywheels/distlib/util.py
caniuseonlywheels/distlib/version.py
caniuseonlywheels/distlib/w32.exe
caniuseonlywheels/distlib/w64-arm.exe
caniuseonlywheels/distlib/w64.exe
caniuseonlywheels/distlib/wheel.py
caniuseonlywheels/overrides.json
caniuseonlywheels/overrides.txt
caniuseonlywheels/projects.py
caniuseonlywheels/pypi.py
caniuseonlywheels-1.0.11.dist-info/entry_points.txt
caniuseonlywheels-1.0.11.dist-info/LICENSE
caniuseonlywheels-1.0.11.dist-info/WHEEL
caniuseonlywheels-1.0.11.dist-info/METADATA
caniuseonlywheels-1.0.11.dist-info/RECORD
