Metadata-Version: 2.1
Name: caniuseonlywheels
Version: 1.0.11
Summary: Can I switch to installing only using wheels and never sdist?
Home-page: https://github.com/matthewdeanmartin/caniuseonlywheels
License: MIT
Keywords: supply-chain,wheels
Author: Matthew Martin
Author-email: matthewdeanmartin@gmail.com
Requires-Python: >=3.3,<4.0
Classifier: Development Status :: 4 - Beta
Classifier: Intended Audience :: Developers
Classifier: License :: OSI Approved :: MIT License
Classifier: Operating System :: OS Independent
Classifier: Programming Language :: Python
Classifier: Programming Language :: Python :: 3
Classifier: Programming Language :: Python :: 3.10
Classifier: Programming Language :: Python :: 3.3
Classifier: Programming Language :: Python :: 3.4
Classifier: Programming Language :: Python :: 3.5
Classifier: Programming Language :: Python :: 3.6
Classifier: Programming Language :: Python :: 3.7
Classifier: Programming Language :: Python :: 3.8
Classifier: Programming Language :: Python :: 3.9
Requires-Dist: certifi
Requires-Dist: packaging
Requires-Dist: requests
Requires-Dist: setuptools
Project-URL: Bug Tracker, https://github.com/matthewdeanmartin/caniuseonlywheels/issues
Project-URL: Change Log, https://github.com/matthewdeanmartin/caniuseonlywheels/blob/main/CHANGES.md
Project-URL: Documentation, https://github.com/matthewdeanmartin/caniuseonlywheels
Project-URL: Repository, https://github.com/matthewdeanmartin/caniuseonlywheels
